CHANGELOG.md
LICENSE
MANIFEST.in
Makefile
README.md
setup.cfg
setup.py
tox.ini
px_snowball/__init__.py
px_snowball/decorators.py
px_snowball/exceptions.py
px_snowball/runners.py
px_snowball/storages.py
px_snowball/utils.py
px_snowball/wrappers.py
px_snowball.egg-info/PKG-INFO
px_snowball.egg-info/SOURCES.txt
px_snowball.egg-info/dependency_links.txt
px_snowball.egg-info/requires.txt
px_snowball.egg-info/top_level.txt